[["Inicio subrutina", {"Num": 5005, "Pgr": 242, "Tol": 4}], ["Datos platina", {"Row": 6, "Col": 8, "Xdt": 1.147, "Ydt": 0.91, "Xbt": 0.198, "Ybt": 0.198, "Xof": 0.0, "Yof": 0.0, "Xdm": 10.0, "Ydm": 6.0}], ["        Comentario", {"Blk": false, "Com": "DESBASTE GRADA"}], ["            Movimiento lineal", {"Blk": false, "Sys": "INCREMENTAL", "Mov": "CORTE", "Xnd": 0.2645, "Ynd": 0.146, "Znd": -0.045, "Fed": 0.005, "Rep": "", "Com": ""}], ["            Movimiento lineal", {"Blk": false, "Sys": "", "Mov": "", "Xnd": -0.529, "Ynd": "", "Znd": "", "Fed": 0.02, "Rep": "", "Com": ""}], ["            Movimiento lineal", {"Blk": false, "Sys": "", "Mov": "", "Xnd": "", "Ynd": -0.292, "Znd": "", "Fed": "", "Rep": "", "Com": ""}], ["            Movimiento lineal", {"Blk": false, "Sys": "", "Mov": "", "Xnd": 0.529, "Ynd": "", "Znd": "", "Fed": "", "Rep": "", "Com": ""}], ["            Movimiento lineal", {"Blk": false, "Sys": "", "Mov": "", "Xnd": "", "Ynd": 0.292, "Znd": "", "Fed": "", "Rep": "", "Com": ""}], ["            Movimiento lineal", {"Blk": false, "Sys": "", "Mov": "", "Xnd": -0.2645, "Ynd": -0.146, "Znd": "", "Fed": "", "Rep": "", "Com": ""}], ["            Movimiento lineal", {"Blk": false, "Sys": "", "Mov": "", "Xnd": 0.2645, "Ynd": 0.146, "Znd": -0.015, "Fed": 0.005, "Rep": "", "Com": ""}], ["            Movimiento lineal", {"Blk": false, "Sys": "", "Mov": "", "Xnd": -0.529, "Ynd": "", "Znd": "", "Fed": 0.02, "Rep": "", "Com": ""}], ["            Movimiento lineal", {"Blk": false, "Sys": "", "Mov": "", "Xnd": "", "Ynd": -0.292, "Znd": "", "Fed": "", "Rep": "", "Com": ""}], ["            Movimiento lineal", {"Blk": false, "Sys": "", "Mov": "", "Xnd": 0.529, "Ynd": "", "Znd": "", "Fed": "", "Rep": "", "Com": ""}], ["            Movimiento lineal", {"Blk": false, "Sys": "", "Mov": "", "Xnd": "", "Ynd": 0.292, "Znd": "", "Fed": "", "Rep": "", "Com": ""}], ["            Movimiento lineal", {"Blk": false, "Sys": "", "Mov": "", "Xnd": -0.2645, "Ynd": -0.146, "Znd": "", "Fed": "", "Rep": "", "Com": ""}], ["            Movimiento lineal", {"Blk": false, "Sys": "", "Mov": "", "Xnd": 0.2645, "Ynd": 0.146, "Znd": -0.015, "Fed": 0.005, "Rep": "", "Com": ""}], ["            Movimiento lineal", {"Blk": false, "Sys": "", "Mov": "", "Xnd": -0.529, "Ynd": "", "Znd": "", "Fed": 0.02, "Rep": "", "Com": ""}], ["            Movimiento lineal", {"Blk": false, "Sys": "", "Mov": "", "Xnd": "", "Ynd": -0.292, "Znd": "", "Fed": "", "Rep": "", "Com": ""}], ["            Movimiento lineal", {"Blk": false, "Sys": "", "Mov": "", "Xnd": 0.529, "Ynd": "", "Znd": "", "Fed": "", "Rep": "", "Com": ""}], ["            Movimiento lineal", {"Blk": false, "Sys": "", "Mov": "", "Xnd": "", "Ynd": 0.292, "Znd": "", "Fed": "", "Rep": "", "Com": ""}], ["            Movimiento lineal", {"Blk": false, "Sys": "", "Mov": "", "Xnd": -0.2645, "Ynd": -0.146, "Znd": "", "Fed": "", "Rep": "", "Com": ""}], ["            Movimiento lineal", {"Blk": false, "Sys": "", "Mov": "", "Xnd": 0.2645, "Ynd": 0.146, "Znd": -0.015, "Fed": 0.005, "Rep": "", "Com": ""}], ["            Movimiento lineal", {"Blk": false, "Sys": "", "Mov": "", "Xnd": -0.529, "Ynd": "", "Znd": "", "Fed": 0.02, "Rep": "", "Com": ""}], ["            Movimiento lineal", {"Blk": false, "Sys": "", "Mov": "", "Xnd": "", "Ynd": -0.292, "Znd": "", "Fed": "", "Rep": "", "Com": ""}], ["            Movimiento lineal", {"Blk": false, "Sys": "", "Mov": "", "Xnd": 0.529, "Ynd": "", "Znd": "", "Fed": "", "Rep": "", "Com": ""}], ["            Movimiento lineal", {"Blk": false, "Sys": "", "Mov": "", "Xnd": "", "Ynd": 0.292, "Znd": "", "Fed": "", "Rep": "", "Com": ""}], ["            Movimiento lineal", {"Blk": false, "Sys": "", "Mov": "", "Xnd": -0.2645, "Ynd": -0.146, "Znd": "", "Fed": "", "Rep": "", "Com": ""}], ["            C\u00f3digo libre", {"Blk": false, "Fre": ""}], ["        Comentario", {"Blk": false, "Com": "DESBASTE FONDO"}], ["            Movimiento lineal", {"Blk": false, "Sys": "", "Mov": "", "Xnd": 0.215, "Ynd": 0.097, "Znd": -0.015, "Fed": 0.005, "Rep": "", "Com": ""}], ["            Movimiento lineal", {"Blk": false, "Sys": "", "Mov": "", "Xnd": -0.43, "Ynd": "", "Znd": "", "Fed": 0.02, "Rep": "", "Com": ""}], ["            Movimiento lineal", {"Blk": false, "Sys": "", "Mov": "", "Xnd": "", "Ynd": -0.194, "Znd": "", "Fed": "", "Rep": "", "Com": ""}], ["            Movimiento lineal", {"Blk": false, "Sys": "", "Mov": "", "Xnd": 0.43, "Ynd": "", "Znd": "", "Fed": "", "Rep": "", "Com": ""}], ["            Movimiento lineal", {"Blk": false, "Sys": "", "Mov": "", "Xnd": "", "Ynd": 0.194, "Znd": "", "Fed": "", "Rep": "", "Com": ""}], ["            Movimiento lineal", {"Blk": false, "Sys": "", "Mov": "", "Xnd": -0.215, "Ynd": -0.097, "Znd": "", "Fed": "", "Rep": "", "Com": ""}], ["            Movimiento lineal", {"Blk": false, "Sys": "", "Mov": "", "Xnd": 0.215, "Ynd": 0.097, "Znd": -0.015, "Fed": 0.005, "Rep": "", "Com": ""}], ["            Movimiento lineal", {"Blk": false, "Sys": "", "Mov": "", "Xnd": -0.43, "Ynd": "", "Znd": "", "Fed": 0.02, "Rep": "", "Com": ""}], ["            Movimiento lineal", {"Blk": false, "Sys": "", "Mov": "", "Xnd": "", "Ynd": -0.194, "Znd": "", "Fed": "", "Rep": "", "Com": ""}], ["            Movimiento lineal", {"Blk": false, "Sys": "", "Mov": "", "Xnd": 0.43, "Ynd": "", "Znd": "", "Fed": "", "Rep": "", "Com": ""}], ["            Movimiento lineal", {"Blk": false, "Sys": "", "Mov": "", "Xnd": "", "Ynd": 0.194, "Znd": "", "Fed": "", "Rep": "", "Com": ""}], ["            Movimiento lineal", {"Blk": false, "Sys": "", "Mov": "", "Xnd": -0.215, "Ynd": -0.097, "Znd": "", "Fed": "", "Rep": "", "Com": ""}], ["            Movimiento lineal", {"Blk": false, "Sys": "", "Mov": "", "Xnd": 0.215, "Ynd": 0.097, "Znd": -0.015, "Fed": 0.005, "Rep": "", "Com": ""}], ["            Movimiento lineal", {"Blk": false, "Sys": "", "Mov": "", "Xnd": -0.43, "Ynd": "", "Znd": "", "Fed": 0.02, "Rep": "", "Com": ""}], ["            Movimiento lineal", {"Blk": false, "Sys": "", "Mov": "", "Xnd": "", "Ynd": -0.194, "Znd": "", "Fed": "", "Rep": "", "Com": ""}], ["            Movimiento lineal", {"Blk": false, "Sys": "", "Mov": "", "Xnd": 0.43, "Ynd": "", "Znd": "", "Fed": "", "Rep": "", "Com": ""}], ["            Movimiento lineal", {"Blk": false, "Sys": "", "Mov": "", "Xnd": "", "Ynd": 0.194, "Znd": "", "Fed": "", "Rep": "", "Com": ""}], ["            Movimiento lineal", {"Blk": false, "Sys": "", "Mov": "", "Xnd": -0.215, "Ynd": -0.097, "Znd": "", "Fed": "", "Rep": "", "Com": ""}], ["            Movimiento lineal", {"Blk": false, "Sys": "", "Mov": "", "Xnd": 0.215, "Ynd": 0.097, "Znd": -0.015, "Fed": 0.005, "Rep": "", "Com": ""}], ["            Movimiento lineal", {"Blk": false, "Sys": "", "Mov": "", "Xnd": -0.43, "Ynd": "", "Znd": "", "Fed": 0.02, "Rep": "", "Com": ""}], ["            Movimiento lineal", {"Blk": false, "Sys": "", "Mov": "", "Xnd": "", "Ynd": -0.194, "Znd": "", "Fed": "", "Rep": "", "Com": ""}], ["            Movimiento lineal", {"Blk": false, "Sys": "", "Mov": "", "Xnd": 0.43, "Ynd": "", "Znd": "", "Fed": "", "Rep": "", "Com": ""}], ["            Movimiento lineal", {"Blk": false, "Sys": "", "Mov": "", "Xnd": "", "Ynd": 0.194, "Znd": "", "Fed": "", "Rep": "", "Com": ""}], ["            Movimiento lineal", {"Blk": false, "Sys": "", "Mov": "", "Xnd": -0.215, "Ynd": -0.097, "Znd": "", "Fed": "", "Rep": "", "Com": ""}], ["            Movimiento lineal", {"Blk": false, "Sys": "", "Mov": "", "Xnd": 0.215, "Ynd": 0.097, "Znd": -0.01, "Fed": 0.005, "Rep": "", "Com": ""}], ["            Movimiento lineal", {"Blk": false, "Sys": "", "Mov": "", "Xnd": -0.43, "Ynd": "", "Znd": "", "Fed": 0.02, "Rep": "", "Com": ""}], ["            Movimiento lineal", {"Blk": false, "Sys": "", "Mov": "", "Xnd": "", "Ynd": -0.194, "Znd": "", "Fed": "", "Rep": "", "Com": ""}], ["            Movimiento lineal", {"Blk": false, "Sys": "", "Mov": "", "Xnd": 0.43, "Ynd": "", "Znd": "", "Fed": "", "Rep": "", "Com": ""}], ["            Movimiento lineal", {"Blk": false, "Sys": "", "Mov": "", "Xnd": "", "Ynd": 0.194, "Znd": "", "Fed": "", "Rep": "", "Com": ""}], ["            Movimiento lineal", {"Blk": false, "Sys": "", "Mov": "", "Xnd": -0.215, "Ynd": -0.097, "Znd": "", "Fed": "", "Rep": "", "Com": ""}], ["            Movimiento lineal", {"Blk": false, "Sys": "", "Mov": "R\u00c1PIDO", "Xnd": "", "Ynd": "", "Znd": 0.16, "Fed": "", "Rep": "", "Com": ""}], ["Fin", {}]]