[["Inicio de programa", {"Prt": "C470 3 REMACHES P1547", "Pgr": "1259", "Dsc": "PLATINA POSTERIOR", "Mch": "MAZAK", "Dia": 0.0, "Lgt": 0.0, "Chk": 0.0, "Cof": "DERECHA", "Wrk": "G55 (PRENSA PRECISION)"}], [" ", {"Fre": " ", "Sde": "$1"}], ["    Llamar herramienta", {"Tol": 1, "Typ": "FRESA", "Dia": 0.375, "Spc": "-", "Sde": "$1", "Xin": -1.0, "Yin": -4.97, "Zin": 0.5, "Mcd": "NO", "Com": "-", "Blk": false}], ["        Giro del husillo", {"Spd": 3000, "Rot": "NORMAL", "Sde": "$1", "Blk": false}], ["        Comentario", {"Com": "VACIADO", "Sde": "$1", "Blk": false}], ["        L\u00ednea subrutinas", {"Sub": 8089, "Qty": 5, "Spc": -1.6, "Axs": "COLUMNAS", "Xin": -1.0, "Yin": -4.97, "Zin": 0.05, "Rep": 1, "Ubk": 1, "Cnt": 1, "Sec": "NO", "Mtx": [[-1.0, -4.97], [-2.6, -4.97], [-4.2, -4.97], [-5.800000000000001, -4.97], [-7.4, -4.97]], "Blk": false}], ["        L\u00ednea subrutinas", {"Sub": 8090, "Qty": 6, "Spc": 1.6, "Axs": "COLUMNAS", "Xin": -9.0, "Yin": -4.15, "Zin": 0.05, "Rep": 1, "Ubk": 0, "Cnt": 6, "Sec": "NO", "Mtx": [[-9.0, -4.15], [-7.4, -4.15], [-5.800000000000001, -4.15], [-4.200000000000001, -4.15], [-2.600000000000001, -4.15], [-1.0000000000000009, -4.15]], "Blk": false}], ["        L\u00ednea subrutinas", {"Sub": 8089, "Qty": 5, "Spc": -1.6, "Axs": "COLUMNAS", "Xin": -1.0, "Yin": -3.41, "Zin": 0.05, "Rep": 1, "Ubk": 1, "Cnt": 12, "Sec": "NO", "Mtx": [[-1.0, -3.41], [-2.6, -3.41], [-4.2, -3.41], [-5.800000000000001, -3.41], [-7.4, -3.41]], "Blk": false}], ["        L\u00ednea subrutinas", {"Sub": 8090, "Qty": 6, "Spc": 1.6, "Axs": "COLUMNAS", "Xin": -9.0, "Yin": -2.59, "Zin": 0.05, "Rep": 1, "Ubk": 0, "Cnt": 17, "Sec": "NO", "Mtx": [[-9.0, -2.59], [-7.4, -2.59], [-5.800000000000001, -2.59], [-4.200000000000001, -2.59], [-2.600000000000001, -2.59], [-1.0000000000000009, -2.59]], "Blk": false}], ["        L\u00ednea subrutinas", {"Sub": 8089, "Qty": 5, "Spc": -1.6, "Axs": "COLUMNAS", "Xin": -1.0, "Yin": -1.85, "Zin": 0.05, "Rep": 1, "Ubk": 1, "Cnt": 23, "Sec": "NO", "Mtx": [[-1.0, -1.85], [-2.6, -1.85], [-4.2, -1.85], [-5.800000000000001, -1.85], [-7.4, -1.85]], "Blk": false}], ["        L\u00ednea subrutinas", {"Sub": 8090, "Qty": 6, "Spc": 1.6, "Axs": "COLUMNAS", "Xin": -9.0, "Yin": -1.03, "Zin": 0.05, "Rep": 1, "Ubk": 0, "Cnt": 28, "Sec": "NO", "Mtx": [[-9.0, -1.03], [-7.4, -1.03], [-5.800000000000001, -1.03], [-4.200000000000001, -1.03], [-2.600000000000001, -1.03], [-1.0000000000000009, -1.03]], "Blk": false}], ["    Cerrar herramienta", {"Tol": 1, "Sde": "$1", "Dia": 0.0, "Blk": false}], [" ", {"Fre": " ", "Sde": "$1"}], ["Fin de programa", {"Mta": true, "Bar": 0.0, "Lgt": 0.0, "Chk": 0.0, "Cof": "DERECHA", "Tol": 1, "Typ": "FRESA", "Dia": 0.375, "Spc": "-", "Xps": -1.0, "Yps": -4.97, "Zps": 0.5}]]