[["Inicio subrutina", {"Num": 7992, "Pgr": 1219, "Tol": 2}], ["        Comentario", {"Blk": false, "Com": "ACABADO ESQUINA EXTERIOR"}], ["            Movimiento lineal", {"Blk": false, "Sys": "INCREMENTAL", "Mov": "R\u00c1PIDO", "Xnd": "", "Ynd": "", "Znd": -0.35, "Fed": "", "Rep": "", "Com": ""}], ["            Movimiento lineal", {"Blk": false, "Sys": "", "Mov": "CORTE", "Xnd": 0.0333, "Ynd": -0.1125, "Znd": "", "Fed": 0.02, "Rep": "", "Com": "IZQUIERDA"}], ["            Movimiento lineal", {"Blk": false, "Sys": "", "Mov": "CORTE", "Xnd": 0.2027, "Ynd": "", "Znd": "", "Fed": 0.003, "Rep": "", "Com": ""}], ["            Movimiento lineal", {"Blk": false, "Sys": "", "Mov": "", "Xnd": "", "Ynd": 0.2423, "Znd": "", "Fed": "", "Rep": "", "Com": ""}], ["            Movimiento lineal", {"Blk": false, "Sys": "", "Mov": "R\u00c1PIDO", "Xnd": -0.2027, "Ynd": "", "Znd": "", "Fed": "", "Rep": "", "Com": ""}], ["            Movimiento lineal", {"Blk": false, "Sys": "", "Mov": "", "Xnd": "", "Ynd": -0.2423, "Znd": -0.35, "Fed": "", "Rep": "", "Com": ""}], ["            Movimiento lineal", {"Blk": false, "Sys": "", "Mov": "CORTE", "Xnd": 0.2027, "Ynd": "", "Znd": "", "Fed": 0.003, "Rep": "", "Com": ""}], ["            Movimiento lineal", {"Blk": false, "Sys": "", "Mov": "", "Xnd": "", "Ynd": 0.2423, "Znd": "", "Fed": "", "Rep": "", "Com": ""}], ["            Movimiento lineal", {"Blk": false, "Sys": "", "Mov": "R\u00c1PIDO", "Xnd": -0.1125, "Ynd": 0.0333, "Znd": "", "Fed": "", "Rep": "", "Com": "CANCELAR"}], ["Fin", {}]]