[["Inicio de programa", {"Prt": "PLUG T18-0142", "Pgr": "3027", "Dsc": "TORNEADO", "Mch": "A16", "Dia": 0.25, "Lgt": 1.707, "Chk": 0.0, "Cof": "DERECHA", "Wrk": "G50 (TORNO)"}], [" ", {"Fre": " ", "Sde": "$1"}], ["    Llamar herramienta", {"Tol": 13, "Typ": "CUCHILLA", "Dia": 0.0, "Spc": "-", "Sde": "$1", "Xin": 0.0, "Yin": 0.0, "Zin": -0.02, "Mcd": "NO", "Com": "-", "Blk": false}], ["        Comentario", {"Com": "CONO", "Sde": "$1", "Blk": false}], ["        Torneado lineal", {"Xin": "", "Zin": 0.0, "Fed": "", "Seq": 0.0, "Mov": "", "Sde": "$1", "Blk": false}], ["        Torneado lineal", {"Xin": -0.01, "Zin": "", "Fed": 0.005, "Seq": 0.0, "Mov": "CORTE", "Sde": "$1", "Blk": false}], ["        Torneado lineal", {"Xin": 0.069, "Zin": "", "Fed": "", "Seq": 0.0, "Mov": "", "Sde": "$1", "Blk": false}], ["        Torneado radial", {"Xin": 0.159, "Zin": 0.045, "Fed": 0.003, "Xcn": 0.045, "Zcn": "", "Mov": "A FAVOR", "Sde": "$1", "Blk": false}], ["        Torneado lineal", {"Xin": "", "Zin": 0.41, "Fed": "", "Seq": 0.0, "Mov": "CORTE", "Sde": "$1", "Blk": false}], ["        Torneado lineal", {"Xin": 0.125, "Zin": 0.427, "Fed": "", "Seq": 0.0, "Mov": "", "Sde": "$1", "Blk": false}], ["        Torneado radial", {"Xin": 0.125, "Zin": 0.457, "Fed": "", "Xcn": 0.02, "Zcn": "", "Mov": "EN CONTRA", "Sde": "$1", "Blk": false}], ["        Torneado lineal", {"Xin": 0.21, "Zin": 0.497, "Fed": "", "Seq": 0.0, "Mov": "CORTE", "Sde": "$1", "Blk": false}], ["    Cerrar herramienta", {"Tol": 13, "Sde": "$1", "Dia": 0.25, "Blk": false}], [" ", {"Fre": " ", "Sde": "$1"}], ["    Llamar herramienta", {"Tol": 12, "Typ": "CUCHILLA", "Dia": 0.0, "Spc": "-", "Sde": "$1", "Xin": 0.0, "Yin": 0.0, "Zin": 0.47, "Mcd": "NO", "Com": "-", "Blk": false}], ["        Comentario", {"Com": "ESPIGA", "Sde": "$1", "Blk": false}], ["        Torneado lineal", {"Xin": 0.2, "Zin": "", "Fed": "", "Seq": 0.0, "Mov": "", "Sde": "$1", "Blk": false}], ["        Torneado lineal", {"Xin": "", "Zin": 1.492, "Fed": 0.003, "Seq": 0.0, "Mov": "CORTE", "Sde": "$1", "Blk": false}], ["        Torneado lineal", {"Xin": 0.128, "Zin": 1.528, "Fed": "", "Seq": 0.0, "Mov": "", "Sde": "$1", "Blk": false}], ["        Torneado lineal", {"Xin": "", "Zin": 1.72, "Fed": "", "Seq": 0.0, "Mov": "", "Sde": "$1", "Blk": false}], ["    Cerrar herramienta", {"Tol": 12, "Sde": "$1", "Dia": 0.25, "Blk": false}], [" ", {"Fre": " ", "Sde": "$1"}], ["    Llamar herramienta", {"Tol": 14, "Typ": "CUCHILLA", "Dia": 0.0, "Spc": "-", "Sde": "$1", "Xin": 0.0, "Yin": 0.0, "Zin": 1.492, "Mcd": "NO", "Com": "-", "Blk": false}], ["        Comentario", {"Com": "ESPIGA", "Sde": "$1", "Blk": false}], ["        Torneado lineal", {"Xin": 0.22, "Zin": "", "Fed": "", "Seq": 0.0, "Mov": "", "Sde": "$1", "Blk": false}], ["        Torneado lineal", {"Xin": 0.084, "Zin": "", "Fed": 0.003, "Seq": 0.0, "Mov": "CORTE", "Sde": "$1", "Blk": false}], ["        Torneado lineal", {"Xin": "", "Zin": 1.527, "Fed": "", "Seq": 0.0, "Mov": "", "Sde": "$1", "Blk": false}], ["    Cerrar herramienta", {"Tol": 14, "Sde": "$1", "Dia": 0.25, "Blk": false}], [" ", {"Fre": " ", "Sde": "$1"}], ["    Llamar herramienta", {"Tol": 15, "Typ": "CUCHILLA", "Dia": 0, "Spc": "ROSCAR", "Sde": "$1", "Xin": 0.128, "Yin": 0, "Zin": 1.527, "Mcd": "NO", "Com": "-", "Blk": false}], ["        Giro del husillo", {"Spd": 1500, "Rot": "NORMAL", "Sde": "$1", "Blk": false}], ["        Ciclo roscado", {"Zin": 1.527, "Znd": 1.707, "Thd": "6-32", "Typ": "EXTERNA", "Pos": "POSITIVA", "Rgh": "S\u00cd", "Dia": 0.25, "Blk": false}], ["    Cerrar herramienta", {"Tol": 15, "Sde": "$1", "Dia": 0.25, "Blk": false}], [" ", {"Fre": " ", "Sde": "$1"}], ["        Tronzado de pieza", {"Dia": 0.128, "Cfr": 0.03, "Lgt": 1.707, "Chk": 0.0, "Cof": "DERECHA", "Blk": false}], [" ", {"Fre": " ", "Sde": "$1"}], ["Fin de programa", {"Mta": true, "Bar": 0.25, "Lgt": 1.707, "Chk": 0.0, "Cof": "DERECHA", "Tol": 13, "Typ": "CUCHILLA", "Dia": 0.0, "Spc": "-", "Xps": 0.0, "Yps": 0.0, "Zps": -0.02}]]