[["Inicio", {"Num": 965, "Prt": "T-10D", "Dsc": "CONO Y CARAS", "Typ": "HARDINGE"}], ["    Herramienta", {"Blk": false, "Tol": 1, "Typ": "CUCHILLA DERECHA", "Dia": 0.0, "Xin": -16.0, "Zin": -0.5, "Rpm": 4000}], ["        Comentario", {"Blk": false, "Com": "CONO"}], ["            Movimiento lineal", {"Blk": false, "Mov": "", "Xnd": "", "Znd": 0.1, "Fed": "", "Vrt": "", "Dim": ""}], ["            Movimiento lineal", {"Blk": false, "Mov": "", "Xnd": 0.074, "Znd": "", "Fed": "", "Vrt": "", "Dim": ""}], ["            Movimiento lineal", {"Blk": false, "Mov": "CORTE", "Xnd": "", "Znd": 0.03, "Fed": 0.02, "Vrt": "", "Dim": ""}], ["            Movimiento lineal", {"Blk": false, "Mov": "", "Xnd": 0.161, "Znd": -0.48, "Fed": 0.003, "Vrt": "", "Dim": ""}], ["            Movimiento lineal", {"Blk": false, "Mov": "", "Xnd": 0.342, "Znd": -0.689, "Fed": "", "Vrt": "", "Dim": ""}], ["            Movimiento lineal", {"Blk": false, "Mov": "", "Xnd": "", "Znd": -0.8, "Fed": "", "Vrt": "", "Dim": ""}], ["            Movimiento lineal", {"Blk": false, "Mov": "", "Xnd": 0.352, "Znd": -0.85, "Fed": "", "Vrt": "", "Dim": ""}], ["            Movimiento lineal", {"Blk": false, "Mov": "R\u00c1PIDO", "Xnd": 2.0, "Znd": "", "Fed": "", "Vrt": "", "Dim": ""}], ["            Iniciar fresados", {"Blk": false}], ["    Herramienta", {"Blk": false, "Tol": 3, "Typ": "FRESA PLANA", "Dia": 0.25, "Xin": 0.0, "Zin": 0.5, "Rpm": 0}], ["        Comentario", {"Blk": false, "Com": "CARA NEGATIVA"}], ["            Movimiento lineal", {"Blk": false, "Mov": "", "Xnd": -0.25, "Znd": 0.15, "Fed": "", "Vrt": "", "Dim": ""}], ["            Cara", {"Blk": false, "Wdt": 0.039, "Lgt": 0.274, "Ang": 9.0, "Dia": 0.059, "Fed": 20.0, "Dpt": 0.015, "Dyr": "ALTERNADO", "Pos": "NEGATIVA", "Xad": 0.0, "Zad": 0.0}], ["            Movimiento lineal", {"Blk": false, "Mov": "", "Xnd": 0.1, "Znd": "", "Fed": "", "Vrt": "", "Dim": ""}], ["    Herramienta", {"Blk": false, "Tol": 4, "Typ": "FRESA PLANA", "Dia": 0.25, "Xin": 0.1, "Zin": 0.125, "Rpm": 0}], ["        Comentario", {"Blk": false, "Com": "CARA POSITIVA"}], ["            Movimiento lineal", {"Blk": false, "Mov": "", "Xnd": 0.25, "Znd": "", "Fed": "", "Vrt": "", "Dim": ""}], ["            Cara", {"Blk": false, "Wdt": 0.039, "Lgt": 0.274, "Ang": 9.0, "Dia": 0.059, "Fed": 20.0, "Dpt": 0.015, "Dyr": "ALTERNADO", "Pos": "POSITIVA", "Xad": 0.0, "Zad": 0.0}], ["            Movimiento lineal", {"Blk": false, "Mov": "R\u00c1PIDO", "Xnd": "", "Znd": 0.5, "Fed": "", "Vrt": "", "Dim": ""}], ["            Movimiento lineal", {"Blk": false, "Mov": "", "Xnd": 6.0, "Znd": "", "Fed": "", "Vrt": "", "Dim": ""}], ["            Finalizar fresados", {"Blk": false}], ["Fin", {}]]