[["Inicio", {"Num": "C-2817-1", "Prt": "GT4-KN0040PP-C1", "Dsc": "PERFORAR CU"}], ["    Herramienta", {"Blk": false, "Tol": 1, "Typ": "BROCA PUNTEAR", "Dia": 0.25, "Xin": 0.0, "Zin": 2.5}], ["        Comentario", {"Blk": false, "Com": "AGUJERO CENTRO"}], ["            Movimiento lineal", {"Blk": false, "Xnd": "", "Znd": 0.05, "Fed": "", "Vrt": "", "Dim": ""}], ["            Perforado sencillo", {"Blk": false, "Dpt": 0.0855, "Fed": 3.0, "Dwl": ""}], ["            Movimiento lineal", {"Blk": false, "Xnd": "", "Znd": 0.5, "Fed": 300.0, "Vrt": "", "Dim": ""}], ["    Herramienta", {"Blk": false, "Tol": 2, "Typ": "BROCA", "Dia": 0.165, "Xin": 0.0, "Zin": 0.5}], ["        Comentario", {"Blk": false, "Com": "AGUJERO .165"}], ["            Movimiento lineal", {"Blk": false, "Xnd": "", "Znd": 0.05, "Fed": "", "Vrt": "", "Dim": ""}], ["            Ciclo perforado", {"Blk": false, "Dpt": 0.547, "Cut": 0.1, "Ang": 90.0, "Fed": 5.0, "Dwl": ""}], ["            Movimiento lineal", {"Blk": false, "Xnd": "", "Znd": 0.5, "Fed": 300.0, "Vrt": "", "Dim": ""}], ["    Herramienta", {"Blk": false, "Tol": 3, "Typ": "BROCA", "Dia": 0.081, "Xin": 0.0, "Zin": 0.5}], ["        Comentario", {"Blk": false, "Com": "AGUJERO .081"}], ["            Movimiento lineal", {"Blk": false, "Xnd": 0.0, "Znd": 0.05, "Fed": "", "Vrt": "", "Dim": ""}], ["            Movimiento lineal", {"Blk": false, "Xnd": "", "Znd": -0.5, "Fed": 100.0, "Vrt": "", "Dim": ""}], ["            Movimiento lineal", {"Blk": false, "Xnd": "", "Znd": -0.646, "Fed": 3.0, "Vrt": "", "Dim": ""}], ["            Movimiento lineal", {"Blk": false, "Xnd": "", "Znd": 0.5, "Fed": 300.0, "Vrt": "", "Dim": ""}], ["Fin", {}]]