[["Inicio subrutina", {"Num": 7666, "Pgr": 1125, "Tol": 2}], ["        Comentario", {"Blk": false, "Com": "DETALLES PUNTA"}], ["            Movimiento lineal", {"Blk": false, "Sys": "INCREMENTAL", "Mov": "R\u00c1PIDO", "Xnd": "", "Ynd": "", "Znd": -0.11, "Fed": "", "Rep": "", "Com": ""}], ["            Movimiento lineal", {"Blk": false, "Sys": "", "Mov": "CORTE", "Xnd": 0.4745, "Ynd": "", "Znd": "", "Fed": 0.005, "Rep": "", "Com": ""}], ["            Movimiento lineal", {"Blk": false, "Sys": "", "Mov": "", "Xnd": "", "Ynd": -0.1515, "Znd": "", "Fed": "", "Rep": "", "Com": ""}], ["            Movimiento lineal", {"Blk": false, "Sys": "", "Mov": "", "Xnd": 0.051, "Ynd": "", "Znd": "", "Fed": "", "Rep": "", "Com": ""}], ["            Movimiento lineal", {"Blk": false, "Sys": "", "Mov": "", "Xnd": "", "Ynd": 0.303, "Znd": "", "Fed": "", "Rep": "", "Com": ""}], ["            Movimiento lineal", {"Blk": false, "Sys": "", "Mov": "", "Xnd": -0.051, "Ynd": "", "Znd": "", "Fed": "", "Rep": "", "Com": ""}], ["            Movimiento lineal", {"Blk": false, "Sys": "", "Mov": "", "Xnd": "", "Ynd": -0.1515, "Znd": "", "Fed": "", "Rep": "", "Com": ""}], ["            Movimiento lineal", {"Blk": false, "Sys": "", "Mov": "", "Xnd": 0.355, "Ynd": "", "Znd": "", "Fed": "", "Rep": "", "Com": ""}], ["            Movimiento lineal", {"Blk": false, "Sys": "", "Mov": "", "Xnd": "", "Ynd": -0.1515, "Znd": "", "Fed": "", "Rep": "", "Com": ""}], ["            Movimiento lineal", {"Blk": false, "Sys": "", "Mov": "", "Xnd": 0.051, "Ynd": "", "Znd": "", "Fed": "", "Rep": "", "Com": ""}], ["            Movimiento lineal", {"Blk": false, "Sys": "", "Mov": "", "Xnd": "", "Ynd": 0.303, "Znd": "", "Fed": "", "Rep": "", "Com": ""}], ["            Movimiento lineal", {"Blk": false, "Sys": "", "Mov": "", "Xnd": -0.051, "Ynd": "", "Znd": "", "Fed": "", "Rep": "", "Com": ""}], ["            Movimiento lineal", {"Blk": false, "Sys": "", "Mov": "", "Xnd": "", "Ynd": -0.1515, "Znd": "", "Fed": "", "Rep": "", "Com": ""}], ["            Movimiento lineal", {"Blk": false, "Sys": "", "Mov": "", "Xnd": 0.354, "Ynd": "", "Znd": "", "Fed": "", "Rep": "", "Com": ""}], ["            Movimiento lineal", {"Blk": false, "Sys": "", "Mov": "", "Xnd": "", "Ynd": -0.1515, "Znd": "", "Fed": "", "Rep": "", "Com": ""}], ["            Movimiento lineal", {"Blk": false, "Sys": "", "Mov": "", "Xnd": 0.051, "Ynd": "", "Znd": "", "Fed": "", "Rep": "", "Com": ""}], ["            Movimiento lineal", {"Blk": false, "Sys": "", "Mov": "", "Xnd": "", "Ynd": 0.303, "Znd": "", "Fed": "", "Rep": "", "Com": ""}], ["            Movimiento lineal", {"Blk": false, "Sys": "", "Mov": "", "Xnd": -0.051, "Ynd": "", "Znd": "", "Fed": "", "Rep": "", "Com": ""}], ["            Movimiento lineal", {"Blk": false, "Sys": "", "Mov": "", "Xnd": "", "Ynd": -0.1515, "Znd": "", "Fed": "", "Rep": "", "Com": ""}], ["            Movimiento lineal", {"Blk": false, "Sys": "", "Mov": "", "Xnd": 0.472, "Ynd": "", "Znd": "", "Fed": "", "Rep": "", "Com": ""}], ["            Movimiento lineal", {"Blk": false, "Sys": "", "Mov": "", "Xnd": "", "Ynd": -0.1515, "Znd": "", "Fed": "", "Rep": "", "Com": ""}], ["            Movimiento lineal", {"Blk": false, "Sys": "", "Mov": "", "Xnd": 0.051, "Ynd": "", "Znd": "", "Fed": "", "Rep": "", "Com": ""}], ["            Movimiento lineal", {"Blk": false, "Sys": "", "Mov": "", "Xnd": "", "Ynd": 0.303, "Znd": "", "Fed": "", "Rep": "", "Com": ""}], ["            Movimiento lineal", {"Blk": false, "Sys": "", "Mov": "", "Xnd": -0.051, "Ynd": "", "Znd": "", "Fed": "", "Rep": "", "Com": ""}], ["            Movimiento lineal", {"Blk": false, "Sys": "", "Mov": "", "Xnd": "", "Ynd": -0.1515, "Znd": "", "Fed": "", "Rep": "", "Com": ""}], ["            Movimiento lineal", {"Blk": false, "Sys": "", "Mov": "", "Xnd": 0.591, "Ynd": "", "Znd": "", "Fed": "", "Rep": "", "Com": ""}], ["            Movimiento lineal", {"Blk": false, "Sys": "", "Mov": "", "Xnd": "", "Ynd": -0.1515, "Znd": "", "Fed": "", "Rep": "", "Com": ""}], ["            Movimiento lineal", {"Blk": false, "Sys": "", "Mov": "", "Xnd": "", "Ynd": 0.0825, "Znd": "", "Fed": "", "Rep": "", "Com": ""}], ["            Movimiento lineal", {"Blk": false, "Sys": "", "Mov": "", "Xnd": 0.366, "Ynd": "", "Znd": "", "Fed": "", "Rep": "", "Com": ""}], ["            Movimiento lineal", {"Blk": false, "Sys": "", "Mov": "", "Xnd": "", "Ynd": -0.0825, "Znd": "", "Fed": "", "Rep": "", "Com": ""}], ["            Movimiento lineal", {"Blk": false, "Sys": "", "Mov": "", "Xnd": "", "Ynd": 0.303, "Znd": "", "Fed": "", "Rep": "", "Com": ""}], ["            Movimiento lineal", {"Blk": false, "Sys": "", "Mov": "", "Xnd": "", "Ynd": -0.0825, "Znd": "", "Fed": "", "Rep": "", "Com": ""}], ["            Movimiento lineal", {"Blk": false, "Sys": "", "Mov": "", "Xnd": -0.366, "Ynd": "", "Znd": "", "Fed": "", "Rep": "", "Com": ""}], ["            Movimiento lineal", {"Blk": false, "Sys": "", "Mov": "", "Xnd": "", "Ynd": 0.0825, "Znd": "", "Fed": "", "Rep": "", "Com": ""}], ["            Movimiento lineal", {"Blk": false, "Sys": "", "Mov": "", "Xnd": "", "Ynd": -0.1515, "Znd": "", "Fed": "", "Rep": "", "Com": ""}], ["            Movimiento lineal", {"Blk": false, "Sys": "", "Mov": "", "Xnd": 1.539, "Ynd": "", "Znd": "", "Fed": "", "Rep": "", "Com": ""}], ["            Movimiento lineal", {"Blk": false, "Sys": "", "Mov": "R\u00c1PIDO", "Xnd": "", "Ynd": "", "Znd": 0.1, "Fed": "", "Rep": "", "Com": ""}], ["            Movimiento lineal", {"Blk": false, "Sys": "", "Mov": "", "Xnd": -3.7855, "Ynd": "", "Znd": "", "Fed": "", "Rep": "", "Com": ""}], ["Fin", {}]]